[
    {
        "q": "Noise levels are measured in?",
        "a": [
            {
                "aText": "Micro sound",
                "isTrue": false
            },
            {
                "aText": "Decibels",
                "isTrue": true
            },
            {
                "aText": "Sysmograph",
                "isTrue": false
            },
            {
                "aText": "Soundwaves",
                "isTrue": false
            }
        ]
    },
    {
        "q": "According to the Bible, who died at the ripe old age of 930?",
        "a": [
            {
                "aText": "Noah",
                "isTrue": false
            },
            {
                "aText": "Adam",
                "isTrue": true
            },
            {
                "aText": "Saul",
                "isTrue": false
            },
            {
                "aText": "David",
                "isTrue": false
            }
        ]
    },
    {
        "q": "What's the highest-pitched instrument in the orchestra? ",
        "a": [
            {
                "aText": "The Piccolo",
                "isTrue": true
            },
            {
                "aText": "The Violin",
                "isTrue": false
            },
            {
                "aText": "The Bass",
                "isTrue": false
            },
            {
                "aText": "The Piano",
                "isTrue": false
            }
        ]
    },
    {
        "q": "Annapolis is the capital of which US state?",
        "a": [
            {
                "aText": "South Carolina",
                "isTrue": false
            },
            {
                "aText": "Wisconsin",
                "isTrue": false
            },
            {
                "aText": "Montana",
                "isTrue": false
            },
            {
                "aText": "Maryland",
                "isTrue": true
            }
        ]
    },
    {
        "q": "In Hayao Miyazaki's 'Spirited Away', the workers that feed coal to the boiler furnace are made from what? ",
        "a": [
            {
                "aText": "Dust",
                "isTrue": false
            },
            {
                "aText": "Charcoal",
                "isTrue": false
            },
            {
                "aText": "Soot",
                "isTrue": true
            },
            {
                "aText": "Wood",
                "isTrue": false
            }
        ]
    }
]